qucirc-0.1.3.dist-info/METADATA
qucirc-0.1.3.dist-info/WHEEL
qucirc/_.cpython-311-x86_64-linux-gnu.so
qucirc/_/__init__.pyi
qucirc/_/ops.pyi
qucirc/__init__.py
qucirc/ops.py
qucirc-0.1.3.dist-info/RECORD
