Metadata-Version: 2.4
Name: qucirc
Version: 0.1.3
Classifier: Programming Language :: Rust
Classifier: Programming Language :: Python :: Implementation :: CPython
Classifier: Programming Language :: Python :: Implementation :: PyPy
Summary: A Python library for quantum circuit construction and manipulation. It is a Python wrapper for the Rust library `qucirc`.
Keywords: quantum,circuit,visualization,python,dyn
Home-Page: https://github.com/YuantianDing/qucirc
Author: YuantianDing <work.yt.ding@gmail.com>
Author-email: Yuantian Ding <dnailzb@outlook.com>
License: MIT
Requires-Python: >=3.8
Project-URL: Source Code, https://github.com/YuantianDing/qucirc
